greenflow_gquant_plugin/__init__.py
greenflow_gquant_plugin/cache.py
greenflow_gquant_plugin/client.py
greenflow_gquant_plugin/node_hdf_cache.py
greenflow_gquant_plugin/analysis/__init__.py
greenflow_gquant_plugin/analysis/barPlotNode.py
greenflow_gquant_plugin/analysis/cumReturnNode.py
greenflow_gquant_plugin/analysis/exportXGBoostNode.py
greenflow_gquant_plugin/analysis/importanceCurve.py
greenflow_gquant_plugin/analysis/linePlotNode.py
greenflow_gquant_plugin/analysis/outCsvNode.py
greenflow_gquant_plugin/analysis/rocCurveNode.py
greenflow_gquant_plugin/analysis/scatterPlotNode.py
greenflow_gquant_plugin/analysis/sharpeRatioNode.py
greenflow_gquant_plugin/backtest/__init__.py
greenflow_gquant_plugin/backtest/simpleBackTest.py
greenflow_gquant_plugin/cuindicator/__init__.py
greenflow_gquant_plugin/cuindicator/ewm.py
greenflow_gquant_plugin/cuindicator/frac_diff.py
greenflow_gquant_plugin/cuindicator/indicator.py
greenflow_gquant_plugin/cuindicator/pewm.py
greenflow_gquant_plugin/cuindicator/rolling.py
greenflow_gquant_plugin/cuindicator/util.py
greenflow_gquant_plugin/cuindicator/windows.py
greenflow_gquant_plugin/dataloader/__init__.py
greenflow_gquant_plugin/dataloader/classificationGenerator.py
greenflow_gquant_plugin/dataloader/csvStockLoader.py
greenflow_gquant_plugin/dataloader/stockMap.py
greenflow_gquant_plugin/dataloader/stockNameLoader.py
greenflow_gquant_plugin/ml/__init__.py
greenflow_gquant_plugin/ml/forestInference.py
greenflow_gquant_plugin/ml/gridRandomSearchNode.py
greenflow_gquant_plugin/ml/splitDataNode.py
greenflow_gquant_plugin/ml/xgboostNode.py
greenflow_gquant_plugin/portofolio/__init__.py
greenflow_gquant_plugin/portofolio/simpleAveragePortOpt.py
greenflow_gquant_plugin/strategy/__init__.py
greenflow_gquant_plugin/strategy/movingAverageStrategyNode.py
greenflow_gquant_plugin/strategy/portExpMovingAverageStrategyNode.py
greenflow_gquant_plugin/strategy/xgboostStrategyNode.py
greenflow_gquant_plugin/transform/__init__.py
greenflow_gquant_plugin-0.0.3.dist-info/METADATA
greenflow_gquant_plugin-0.0.3.dist-info/WHEEL
greenflow_gquant_plugin-0.0.3.dist-info/entry_points.txt
greenflow_gquant_plugin-0.0.3.dist-info/top_level.txt
greenflow_gquant_plugin-0.0.3.dist-info/RECORD
