Metadata-Version: 2.1
Name: greenflow-gquant-plugin
Version: 0.0.3
Summary: UNKNOWN
Home-page: UNKNOWN
Author: UNKNOWN
Author-email: UNKNOWN
License: UNKNOWN
Platform: UNKNOWN
Requires-Dist: greenflow
Requires-Dist: bqplot
Requires-Dist: tables
Requires-Dist: ray[tune]
Requires-Dist: matplotlib
Requires-Dist: ray[default]
Requires-Dist: mplfinance
